<step title="Incoming Request" date="2026-02-05T13:34:49.780" instance="5d4311" url="/api/publish?async=true&amp;deployer=GITHUB_ONE_DEPLOY&amp;type=zip&amp;message=%7B%22type%22%3A%22deployment%22%2C%22sha%22%3A%22265bd2b87b68e266bbf4e20fb1687993f0de8b42%22%2C%22repoName%22%3A%22punkouter26%2FPoNovaWeight%22%2C%22actor%22%3A%22punkouter26%22%2C%22slotName%22%3A%22production%22%2C%22commitMessage%22%3A%22fix%3A%20Remove%20unnecessary%20nonce%20cookie%20settings%20for%20Azure%20OAuth%22%7D" method="POST" type="request" pid="851,1,36" Host="ponovaweight-app.scm.azurewebsites.net" User-Agent="GITHUBACTIONS_DeployWebAppToAzure_cdce2c904e52a65ce3302c4654b23c5f11fa288e1787a9c50576576d299b0c21" Authorization="Bea..." Content-Type="application/octet-stream" Cookie="ARRAffinity=5d43112dac899e79c5f159102c851f071cec9160838765e615962ec31a27c96f;Path=/;HttpOnly;Secure;Domain=ponovaweight-app.scm.azurewebsites.net; ARRAffinitySameSite=5d43112dac899e79c5f159102c851f071cec9160838765e615962ec31a27c96f;Path=/;HttpOnly;SameSite=None;Secure;Domain=ponovaweight-app.scm.azurewebsites.net" Transfer-Encoding="chunked" X-ARR-LOG-ID="d20068eb-0204-43d1-8625-47db948626d1" CLIENT-IP="172.182.225.134:51264" X-SITE-DEPLOYMENT-ID="ponovaweight-app" WAS-DEFAULT-HOSTNAME="ponovaweight-app.scm.azurewebsites.net" X-Forwarded-Proto="https" X-AppService-Proto="https" X-Forwarded-TlsVersion="1.3" X-WAWS-Unencoded-URL="/api/publish?async=true&amp;deployer=GITHUB_ONE_DEPLOY&amp;type=zip&amp;message=%7B%22type%22%3A%22deployment%22%2C%22sha%22%3A%22265bd2b87b68e266bbf4e20fb1687993f0de8b42%22%2C%22repoName%22%3A%22punkouter26%2FPoNovaWeight%22%2C%22actor%22%3A%22punkouter26%22%2C%22slotName%22%3A%22production%22%2C%22commitMessage%22%3A%22fix%3A%20Remove%20unnecessary%20nonce%20cookie%20settings%20for%20Azure%20OAuth%22%7D" X-Client-IP="172.182.225.134" X-Client-Port="51264" >
  <step title="OneDeploy" date="2026-02-05T13:34:49.906" >
    <step title="None repository commit" date="2026-02-05T13:34:49.928" >
      <step title="Commit id: 0f4a3966-8139-4fd8-a4c8-96d5376f7e96" date="2026-02-05T13:34:49.937" Message="N/A" AuthorName="N/A" AuthorEmail="N/A" /><!-- duration: 6ms -->
    </step><!-- duration: 21ms -->
    <step title="Starting PushDeployAsync" date="2026-02-05T13:34:49.958" /><!-- duration: 5ms -->
    <step title="WEBSITE_RUN_FROM_PACKAGE is set to 1. Writing zip to SitePackagesPath" date="2026-02-05T13:34:50.172" /><!-- duration: 9ms -->
    <step title="Copying zip to SitePackages /home/data/SitePackages/20260205133449.zip from request body" date="2026-02-05T13:34:50.198" /><!-- duration: 6ms -->
    <step title="Writing multipart request body to /home/data/SitePackages/20260205133449.zip" date="2026-02-05T13:34:50.209" /><!-- duration: 3ms -->
    <step title="Deleting outdated zip file /home/data/SitePackages/20260205035746.zip" date="2026-02-05T13:34:50.769" /><!-- duration: 16ms -->
    <step title="Start deployment in the background" date="2026-02-05T13:34:50.977" >
      <step title="Acquiring Deployment Lock" date="2026-02-05T13:34:51.229" /><!-- duration: 4ms -->
      <step title="Acquired Deployment Lock" date="2026-02-05T13:34:51.296" /><!-- duration: 5ms -->
    </step><!-- duration: 454ms -->
  </step><!-- duration: 1538ms -->
  <step title="Outgoing response" date="2026-02-05T13:34:51.453" type="response" statusCode="202" statusText="Accepted" /><!-- duration: 6ms -->
</step><!-- duration: 1687ms -->
